buena_sdk/__init__.py
buena_sdk/api_client.py
buena_sdk/api_response.py
buena_sdk/configuration.py
buena_sdk/exceptions.py
buena_sdk/py.typed
buena_sdk/rest.py
buena_sdk/api/__init__.py
buena_sdk/api/default_api.py
buena_sdk/models/__init__.py
buena_sdk/models/api_key.py
buena_sdk/models/create_api_key_request.py
buena_sdk/models/create_lead_request.py
buena_sdk/models/delete_voice_clone_response.py
buena_sdk/models/error.py
buena_sdk/models/health_check200_response.py
buena_sdk/models/lead.py
buena_sdk/models/list_leads200_response.py
buena_sdk/models/update_voice_clone_request.py
buena_sdk/models/update_voice_clone_response.py
buena_sdk/models/update_voice_clone_response_data.py
buena_sdk/models/voice_clone.py
buena_sdk/models/voice_clone_list_response.py
buena_sdk/models/voice_clone_list_response_data.py
buena_sdk/models/voice_clone_response.py
buena_sdk/models/voice_clone_response_data.py
buena_sdk/models/voice_preview_request.py
buena_sdk-1.0.5.dist-info/METADATA
buena_sdk-1.0.5.dist-info/WHEEL
buena_sdk-1.0.5.dist-info/top_level.txt
buena_sdk-1.0.5.dist-info/RECORD
