Metadata-Version: 2.4
Name: buena_sdk
Version: 1.0.5
Summary: Buena.ai API v2
Home-page: https://github.com/Buena-AI/sdks
Author: Buena.ai Support
Author-email: "Buena.ai Support" <support@buena.ai>
License-Expression: MIT
Project-URL: Repository, https://github.com/GIT_USER_ID/GIT_REPO_ID
Keywords: OpenAPI,OpenAPI-Generator,Buena.ai API v2
Requires-Python: >=3.9
Requires-Dist: urllib3<3.0.0,>=2.1.0
Requires-Dist: python-dateutil>=2.8.2
Requires-Dist: pydantic>=2
Requires-Dist: typing-extensions>=4.7.1
Dynamic: author
Dynamic: home-page
